acs_extract_student_assignments.py
acs_extract_student_assignments-1.0.1.dist-info/DESCRIPTION.rst
acs_extract_student_assignments-1.0.1.dist-info/METADATA
acs_extract_student_assignments-1.0.1.dist-info/RECORD
acs_extract_student_assignments-1.0.1.dist-info/WHEEL
acs_extract_student_assignments-1.0.1.dist-info/entry_points.txt
acs_extract_student_assignments-1.0.1.dist-info/metadata.json
acs_extract_student_assignments-1.0.1.dist-info/top_level.txt
