Metadata-Version: 2.0
Name: acs-extract-student-assignments
Version: 1.0.1
Summary: Console app and Python API for extracting assignments from exam archives of our ACS students
Home-page: https://github.com/petarmaric/acs_extract_student_assignments
Author: Petar Maric
Author-email: petarmaric@uns.ac.rs
License: BSD
Platform: UNKNOWN
Classifier: Development Status :: 5 - Production/Stable
Classifier: Environment :: Console
Classifier: Intended Audience :: Developers
Classifier: Intended Audience :: Education
Classifier: License :: OSI Approved :: BSD License
Classifier: Operating System :: OS Independent
Classifier: Programming Language :: Python :: 2.7
Classifier: Topic :: Education
Classifier: Topic :: Utilities
Provides-Extra: dev
Provides-Extra: dev
Requires-Dist: pylint (~=1.9); extra == 'dev'
